dbt_rowlineage/__init__.py
dbt_rowlineage/auto.py
dbt_rowlineage/cli.py
dbt_rowlineage/compiler_patch.py
dbt_rowlineage/config.py
dbt_rowlineage/plugin.py
dbt_rowlineage/runtime_patch.py
dbt_rowlineage/sql_instrumentation.py
dbt_rowlineage/tracer.py
dbt_rowlineage/utils/__init__.py
dbt_rowlineage/utils/sql.py
dbt_rowlineage/utils/uuid.py
dbt_rowlineage/writers/__init__.py
dbt_rowlineage/writers/jsonl_writer.py
dbt_rowlineage/writers/parquet_writer.py
dbt_rowlineage/writers/table_writer.py
dbt_rowlineage-0.1.7.dist-info/licenses/LICENSE
dbt_rowlineage-0.1.7.dist-info/METADATA
dbt_rowlineage-0.1.7.dist-info/WHEEL
dbt_rowlineage-0.1.7.dist-info/entry_points.txt
dbt_rowlineage-0.1.7.dist-info/top_level.txt
dbt_rowlineage-0.1.7.dist-info/RECORD
