Metadata-Version: 2.4
Name: dbt-rowlineage
Version: 0.1.7
Summary: Adapter-agnostic dbt plugin providing row-level lineage tracing
Author-email: RezerBleede <remisharoon.aws@gmail.com>
License:                                  Apache License
Project-URL: Homepage, https://github.com/rezer-bleede/dbt-rowlineage
Project-URL: Repository, https://github.com/rezer-bleede/dbt-rowlineage
Project-URL: Issues, https://github.com/rezer-bleede/dbt-rowlineage/issues
Keywords: dbt,lineage,analytics,data-engineering
Classifier: Development Status :: 4 - Beta
Classifier: Intended Audience :: Developers
Classifier: License :: OSI Approved :: MIT License
Classifier: Programming Language :: Python
Classifier: Programming Language :: Python :: 3
Classifier: Programming Language :: Python :: 3 :: Only
Classifier: Programming Language :: Python :: 3.10
Classifier: Programming Language :: Python :: 3.11
Classifier: Programming Language :: Python :: 3.12
Classifier: Topic :: Database
Classifier: Topic :: Software Development :: Libraries
Requires-Python: >=3.10
License-File: LICENSE
Requires-Dist: dbt-core>=1.7
Requires-Dist: pandas>=1.5
Requires-Dist: pyarrow>=10.0.0
Requires-Dist: sqlglot>=23.0.0
Provides-Extra: dev
Requires-Dist: pytest>=8; extra == "dev"
Requires-Dist: fastapi>=0.110; extra == "dev"
Requires-Dist: uvicorn>=0.27; extra == "dev"
Requires-Dist: psycopg2-binary>=2.9; extra == "dev"
Requires-Dist: httpx>=0.27; extra == "dev"
Dynamic: license-file
